{
    "def_file": "SN32F237F.json",
    "family_uid": "SN32F230",
    "flash": "32764",
    "icon": "images/mcu/sonix.png",
    "max_speed": "50.000",
    "name": "SN32F237F",
    "ram": "4096",
    "sdk_config": "{\"MCU_NAME\":\"SN32F237F\",\"CORE_NAME\":\"M0\",\"_MSDK_HAL_LOW_LEVEL_TARGET_\":\"mikroe\",\"_MSDK_ETH_PHY_CHIP_\":\"NULL\"}",
    "necto_config": "",
    "uid": "SN32F237F",
    "vendor": "SONiX",
    "compiler_flags": "",
    "linker_flags": "",
    "tft_socket": "1",
    "sdk_support": "0",
    "installer_package": "{\"clang-llvm\": \"arm_gcc_clang_sn32f23\", \"gcc_arm_none_eabi\": \"arm_gcc_clang_sn32f23\"}"
}