{
    "def_file": "XMC1302-Q024X0016.json",
    "family_uid": "XMC1300",
    "flash": "16384",
    "icon": "images/mcu/infineon.png",
    "max_speed": "32.000",
    "name": "XMC1302-Q024X0016",
    "ram": "16384",
    "sdk_config": "{\"MCU_NAME\":\"XMC1302-Q024X0016\",\"CORE_NAME\":\"M0\",\"_MSDK_HAL_LOW_LEVEL_TARGET_\":\"mikroe\",\"_MSDK_ETH_PHY_CHIP_\":\"NULL\"}",
    "necto_config": "",
    "uid": "XMC1302-Q024X0016",
    "vendor": "Infineon",
    "compiler_flags": "",
    "linker_flags": "",
    "tft_socket": "1",
    "sdk_support": "0",
    "installer_package": "{\"clang-llvm\": \"arm_gcc_clang_xmc1302_q\", \"gcc_arm_none_eabi\": \"arm_gcc_clang_xmc1302_q\"}"
}