{
    "def_file": "CM2003GN8AE.json",
    "family_uid": "CM2003",
    "flash": "267264",
    "icon": "images/mcu/nuvoton.png",
    "max_speed": "24.000",
    "name": "CM2003GN8AE",
    "ram": "36864",
    "sdk_config": "{\"MCU_NAME\":\"CM2003GN8AE\",\"CORE_NAME\":\"M23\",\"_MSDK_HAL_LOW_LEVEL_TARGET_\":\"mikroe\",\"_MSDK_ETH_PHY_CHIP_\":\"NULL\"}",
    "necto_config": "",
    "uid": "CM2003GN8AE",
    "vendor": "Nuvoton",
    "compiler_flags": "",
    "linker_flags": "",
    "tft_socket": "1",
    "sdk_support": "0",
    "installer_package": "{\"clang-llvm\": \"arm_gcc_clang_cm20\", \"gcc_arm_none_eabi\": \"arm_gcc_clang_cm20\"}"
}