{
    "def_file": "NUC122LC1AN.json",
    "family_uid": "NUVOTON",
    "flash": "32768",
    "icon": "images/mcu/nuvoton.png",
    "max_speed": "60.000",
    "name": "NUC122LC1AN",
    "ram": "4096",
    "sdk_config": "{\"MCU_NAME\": \"NUC122LC1AN\", \"CORE_NAME\": \"M0\", \"_MSDK_HAL_LOW_LEVEL_TARGET_\": \"mikroe\", \"_MSDK_ETH_PHY_CHIP_\": \"NULL\"}",
    "necto_config": "",
    "uid": "NUC122LC1AN",
    "vendor": "Nuvoton",
    "compiler_flags": "",
    "linker_flags": "",
    "tft_socket": "1",
    "sdk_support": "0",
    "installer_package": "{\"clang-llvm\": \"arm_gcc_clang_nuc122\", \"gcc_arm_none_eabi\": \"arm_gcc_clang_nuc122\"}"
}